nfelib/__init__.py
nfelib/bpe/__init__.py
nfelib/bpe/bindings/__init__.py
nfelib/bpe/bindings/v1_0/__init__.py
nfelib/bpe/bindings/v1_0/bpe_tipos_basico_v1_00.py
nfelib/bpe/bindings/v1_0/bpe_tm_v1_00.py
nfelib/bpe/bindings/v1_0/bpe_v1_00.py
nfelib/bpe/bindings/v1_0/cons_sit_bpe_tipos_basico_v1_00.py
nfelib/bpe/bindings/v1_0/cons_sit_bpe_v1_00.py
nfelib/bpe/bindings/v1_0/cons_stat_serv_bpe_tipos_basico_v1_00.py
nfelib/bpe/bindings/v1_0/cons_stat_serv_bpe_v1_00.py
nfelib/bpe/bindings/v1_0/ev_alteracao_poltrona_v1_00.py
nfelib/bpe/bindings/v1_0/ev_canc_bpe_v1_00.py
nfelib/bpe/bindings/v1_0/ev_excesso_bagagem_v1_00.py
nfelib/bpe/bindings/v1_0/ev_nao_emb_bpe_v1_00.py
nfelib/bpe/bindings/v1_0/evento_bpe_tipos_basico_v1_00.py
nfelib/bpe/bindings/v1_0/evento_bpe_v1_00.py
nfelib/bpe/bindings/v1_0/proc_bpe_tm_v1_00.py
nfelib/bpe/bindings/v1_0/proc_bpe_v1_00.py
nfelib/bpe/bindings/v1_0/proc_evento_bpe_v1_00.py
nfelib/bpe/bindings/v1_0/ret_bpe_v1_00.py
nfelib/bpe/bindings/v1_0/ret_cons_sit_bpe_v1_00.py
nfelib/bpe/bindings/v1_0/ret_cons_stat_serv_bpe_v1_00.py
nfelib/bpe/bindings/v1_0/ret_evento_bpe_v1_00.py
nfelib/bpe/bindings/v1_0/tipos_geral_bpe_v1_00.py
nfelib/bpe/bindings/v1_0/xmldsig_core_schema_v1_01.py
nfelib/bpe/schemas/v1_0/bpeTM_v1.00.xsd
nfelib/bpe/schemas/v1_0/bpeTiposBasico_v1.00.xsd
nfelib/bpe/schemas/v1_0/bpe_v1.00.xsd
nfelib/bpe/schemas/v1_0/consSitBPeTiposBasico_v1.00.xsd
nfelib/bpe/schemas/v1_0/consSitBPe_v1.00.xsd
nfelib/bpe/schemas/v1_0/consStatServBPeTiposBasico_v1.00.xsd
nfelib/bpe/schemas/v1_0/consStatServBPe_v1.00.xsd
nfelib/bpe/schemas/v1_0/evAlteracaoPoltrona_v1.00.xsd
nfelib/bpe/schemas/v1_0/evCancBPe_v1.00.xsd
nfelib/bpe/schemas/v1_0/evExcessoBagagem_v1.00.xsd
nfelib/bpe/schemas/v1_0/evNaoEmbBPe_v1.00.xsd
nfelib/bpe/schemas/v1_0/eventoBPeTiposBasico_v1.00.xsd
nfelib/bpe/schemas/v1_0/eventoBPe_v1.00.xsd
nfelib/bpe/schemas/v1_0/procBPeTM_v1.00.xsd
nfelib/bpe/schemas/v1_0/procBPe_v1.00.xsd
nfelib/bpe/schemas/v1_0/procEventoBPe_v1.00.xsd
nfelib-2.4.0.dist-info/licenses/MIT-LICENSE
nfelib-2.4.0.dist-info/METADATA
nfelib-2.4.0.dist-info/WHEEL
nfelib-2.4.0.dist-info/top_level.txt
nfelib-2.4.0.dist-info/RECORD
