Metadata-Version: 2.4
Name: nfelib
Version: 2.4.0
Summary: nfelib: electronic invoicing library for Brazil
Author-email: Raphaël Valyi <raphael.valyi@akretion.com.br>
License: MIT
Project-URL: Homepage, https://github.com/akretion/nfelib
Project-URL: Source, https://github.com/akretion/nfelib
Project-URL: Documentation, https://nfelib.readthedocs.io/
Project-URL: Changelog, https://nfelib.readthedocs.io/en/latest/changelog/
Keywords: e-invoicing,ERP,Odoo,NFe,CTe,MDFe,BPe,NFSe
Classifier: Intended Audience :: Developers
Classifier: License :: OSI Approved :: MIT License
Classifier: Operating System :: OS Independent
Classifier: Programming Language :: Python
Classifier: Programming Language :: Python :: 3
Classifier: Programming Language :: Python :: 3 :: Only
Classifier: Programming Language :: Python :: 3.8
Classifier: Programming Language :: Python :: 3.9
Classifier: Programming Language :: Python :: 3.10
Classifier: Programming Language :: Python :: 3.11
Classifier: Programming Language :: Python :: 3.12
Classifier: Programming Language :: Python :: 3.13
Classifier: Programming Language :: Python :: Implementation :: CPython
Classifier: Programming Language :: Python :: Implementation :: PyPy
Requires-Python: >=3.8
License-File: MIT-LICENSE
Requires-Dist: lxml
Requires-Dist: xsdata
Provides-Extra: sign
Requires-Dist: erpbrasil.assinatura; extra == "sign"
Provides-Extra: pdf
Requires-Dist: brazilfiscalreport; extra == "pdf"
Provides-Extra: soap
Requires-Dist: xsdata[soap]; extra == "soap"
Requires-Dist: erpbrasil.assinatura; extra == "soap"
Requires-Dist: brazil-fiscal-client; extra == "soap"
Provides-Extra: test
Requires-Dist: pre-commit; extra == "test"
Requires-Dist: pytest; extra == "test"
Requires-Dist: pytest-benchmark; extra == "test"
Requires-Dist: pytest-cov; extra == "test"
Requires-Dist: xmldiff; extra == "test"
Requires-Dist: requests; extra == "test"
Requires-Dist: requests_pkcs12; extra == "test"
Requires-Dist: decorator; extra == "test"
Requires-Dist: beautifulsoup4; extra == "test"
Requires-Dist: erpbrasil.assinatura; extra == "test"
Requires-Dist: brazilfiscalreport; extra == "test"
Requires-Dist: beautifulsoup4; extra == "test"
Requires-Dist: pandas; extra == "test"
Requires-Dist: brazil-fiscal-client; extra == "test"
Dynamic: license-file
